douyin_mcp_server/__init__.py
douyin_mcp_server/__main__.py
douyin_mcp_server/douyin_processor.py
douyin_mcp_server/generic_extractor.py
douyin_mcp_server/server.py
douyin_mcp_server/xiaohongshu_processor.py
wanyi_watermark-1.0.1.dist-info/METADATA
wanyi_watermark-1.0.1.dist-info/WHEEL
wanyi_watermark-1.0.1.dist-info/entry_points.txt
wanyi_watermark-1.0.1.dist-info/licenses/LICENSE
wanyi_watermark-1.0.1.dist-info/RECORD
