Metadata-Version: 2.4
Name: wanyi-watermark
Version: 1.0.1
Summary: 百分百一键去水印 - 视频链接解析与媒体资源提取MCP服务器，支持抖音/小红书/通用平台
Project-URL: Homepage, https://github.com/Ryan7t/wanyi-watermark
Project-URL: Repository, https://github.com/Ryan7t/wanyi-watermark
Project-URL: Issues, https://github.com/Ryan7t/wanyi-watermark/issues
Author-email: wanyi <2368077712@qq.com>
License: Apache-2.0
License-File: LICENSE
Classifier: Development Status :: 3 - Alpha
Classifier: Intended Audience :: Developers
Classifier: License :: OSI Approved :: Apache Software License
Classifier: Programming Language :: Python :: 3
Classifier: Programming Language :: Python :: 3.10
Classifier: Programming Language :: Python :: 3.11
Classifier: Programming Language :: Python :: 3.12
Requires-Python: >=3.10
Requires-Dist: dashscope
Requires-Dist: ffmpeg-python
Requires-Dist: mcp>=1.0.0
Requires-Dist: requests
Requires-Dist: tqdm
